fp_orchestrator_utils/__init__.py
fp_orchestrator_utils/cli/__init__.py
fp_orchestrator_utils/cli/har_model_commands.py
fp_orchestrator_utils/cli/main.py
fp_orchestrator_utils/cli/proto_commands.py
fp_orchestrator_utils/orchestrator_client/__init__.py
fp_orchestrator_utils/orchestrator_client/orchestrator_client.py
fp_orchestrator_utils/proto_manager/__init__.py
fp_orchestrator_utils/proto_manager/proto_manager.py
fp_orchestrator_utils/src/__init__.py
fp_orchestrator_utils/src/data_loader/__init__.py
fp_orchestrator_utils/src/data_loader/data_loader.py
fp_orchestrator_utils/src/grpc/__init__.py
fp_orchestrator_utils/src/grpc/audio_service_pb2.py
fp_orchestrator_utils/src/grpc/audio_service_pb2.pyi
fp_orchestrator_utils/src/grpc/audio_service_pb2_grpc.py
fp_orchestrator_utils/src/grpc/imu_service_pb2.py
fp_orchestrator_utils/src/grpc/imu_service_pb2.pyi
fp_orchestrator_utils/src/grpc/imu_service_pb2_grpc.py
fp_orchestrator_utils/src/grpc/orchestrator_service_pb2.py
fp_orchestrator_utils/src/grpc/orchestrator_service_pb2.pyi
fp_orchestrator_utils/src/grpc/orchestrator_service_pb2_grpc.py
fp_orchestrator_utils/src/grpc/rfid_service_pb2.py
fp_orchestrator_utils/src/grpc/rfid_service_pb2.pyi
fp_orchestrator_utils/src/grpc/rfid_service_pb2_grpc.py
fp_orchestrator_utils/src/har_inference/__init__.py
fp_orchestrator_utils/src/har_inference/har_dataset.py
fp_orchestrator_utils/src/har_inference/har_inference.py
fp_orchestrator_utils/src/har_inference/har_model.py
fp_orchestrator_utils/src/har_inference/har_trainer.py
fp_orchestrator_utils/storage/__init__.py
fp_orchestrator_utils/storage/abstractions/__init__.py
fp_orchestrator_utils/storage/abstractions/base.py
fp_orchestrator_utils/storage/s3/__init__.py
fp_orchestrator_utils/storage/s3/s3_service.py
fp_orchestrator_utils-0.4.3.dist-info/licenses/LICENSE
tests/__init__.py
tests/conftest.py
fp_orchestrator_utils-0.4.3.dist-info/METADATA
fp_orchestrator_utils-0.4.3.dist-info/WHEEL
fp_orchestrator_utils-0.4.3.dist-info/entry_points.txt
fp_orchestrator_utils-0.4.3.dist-info/top_level.txt
fp_orchestrator_utils-0.4.3.dist-info/RECORD
