Metadata-Version: 2.4
Name: fp-orchestrator-utils
Version: 0.4.3
Summary: Utilities for the FP Orchestrator, including CLI tools for managing Protocol Buffers, S3 interactions, and HAR model training and inference.
Home-page: https://github.com/RodCaba/fp-orchestrator-utils
Author: Rodrigo
Author-email: rodser4@gmail.com
License: MIT License
Classifier: Programming Language :: Python :: 3
Classifier: License :: OSI Approved :: MIT License
Classifier: Operating System :: OS Independent
Classifier: Development Status :: 4 - Beta
Classifier: Intended Audience :: Developers
Classifier: Topic :: Software Development :: Libraries
Requires-Python: >=3.8
License-File: LICENSE
Requires-Dist: grpcio>=1.73.1
Requires-Dist: grpcio-tools>=1.73.1
Requires-Dist: protobuf>=6.31.1
Requires-Dist: boto3>=1.39.10
Requires-Dist: python-dotenv>=1.0.0
Dynamic: author
Dynamic: author-email
Dynamic: classifier
Dynamic: description
Dynamic: description-content-type
Dynamic: home-page
Dynamic: license
Dynamic: license-file
Dynamic: requires-dist
Dynamic: requires-python
Dynamic: summary
